apPETite/__init__.py
apPETite/run.py
apPETite_UIUCiGEM_2021-0.0.1.dist-info/LICENSE
apPETite_UIUCiGEM_2021-0.0.1.dist-info/METADATA
apPETite_UIUCiGEM_2021-0.0.1.dist-info/WHEEL
apPETite_UIUCiGEM_2021-0.0.1.dist-info/top_level.txt
apPETite_UIUCiGEM_2021-0.0.1.dist-info/RECORD
