Metadata-Version: 2.1
Name: apPETite-UIUCiGEM-2021
Version: 0.0.1
Summary: Python package for the computational portion of the Illinois iGEM Project, apPETite.
Home-page: https://github.com/UIUCiGEM/apPETite-package
Author: Suva Narayan
Author-email: vantagesuvgt8@gmail.com
License: UNKNOWN
Platform: UNKNOWN
Classifier: Programming Language :: Python :: 3
Classifier: License :: OSI Approved :: MIT License
Classifier: Operating System :: OS Independent
Requires-Python: >=3.6
License-File: LICENSE
